acme_config/__init__.py
acme_config/_main.py
acme_config/aws_parameter_store.py
acme_config-0.0.14.dist-info/METADATA
acme_config-0.0.14.dist-info/WHEEL
acme_config-0.0.14.dist-info/entry_points.txt
acme_config-0.0.14.dist-info/top_level.txt
acme_config-0.0.14.dist-info/RECORD
