Metadata-Version: 2.4
Name: acme_config
Version: 0.0.14
Summary: System to store application configuration
Author-email: guner.stan@gmail.com
Project-URL: homepage, https://example.com
Project-URL: repository, https://example.com
Classifier: Programming Language :: Python :: 3.12
Classifier: Programming Language :: Python :: 3.11
Classifier: Programming Language :: Python :: 3.10
Classifier: Programming Language :: Python :: 3.9
Requires-Python: >=3.9
Requires-Dist: python-dotenv
Requires-Dist: boto3
Provides-Extra: dev
Requires-Dist: pytest; extra == "dev"
Requires-Dist: uv; extra == "dev"
Requires-Dist: mkdocs; extra == "dev"
Requires-Dist: mkdocs-material; extra == "dev"
Requires-Dist: mkdocstrings[python]; extra == "dev"
Requires-Dist: jupyterlab; extra == "dev"
